logbee/__init__.py
logbee/config.py
logbee/core.py
logbee/decorators.py
logbee/django_middleware.py
logbee/fastapi_adapter.py
logbee/flask_adapter.py
logbee/models.py
logbee/utils.py
logbee_sdk-0.2.7.dist-info/licenses/LICENSE
logbee_sdk-0.2.7.dist-info/METADATA
logbee_sdk-0.2.7.dist-info/WHEEL
logbee_sdk-0.2.7.dist-info/top_level.txt
logbee_sdk-0.2.7.dist-info/RECORD
