Metadata-Version: 2.4
Name: logbee-sdk
Version: 0.2.7
Summary: SDK for integrating Python applications with Logbee
Home-page: https://github.com/logbee/logbee-sdk-py
Author: Logbee
Author-email: info@logbee.dev
License: MIT
Keywords: logbee,logging,monitoring,errors,api
Classifier: Development Status :: 4 - Beta
Classifier: Intended Audience :: Developers
Classifier: License :: OSI Approved :: MIT License
Classifier: Natural Language :: English
Classifier: Programming Language :: Python :: 3
Classifier: Programming Language :: Python :: 3.7
Classifier: Programming Language :: Python :: 3.8
Classifier: Programming Language :: Python :: 3.9
Classifier: Programming Language :: Python :: 3.10
Classifier: Programming Language :: Python :: 3.11
Classifier: Programming Language :: Python :: 3.12
Requires-Python: >=3.7
License-File: LICENSE
Requires-Dist: requests>=2.25.0
Provides-Extra: flask
Requires-Dist: flask>=2.0.0; extra == "flask"
Provides-Extra: fastapi
Requires-Dist: fastapi>=0.68.0; extra == "fastapi"
Provides-Extra: django
Requires-Dist: django>=3.2.0; extra == "django"
Provides-Extra: all
Requires-Dist: flask>=2.0.0; extra == "all"
Requires-Dist: fastapi>=0.68.0; extra == "all"
Requires-Dist: django>=3.2.0; extra == "all"
Provides-Extra: dev
Requires-Dist: pytest>=6.2.0; extra == "dev"
Requires-Dist: pytest-cov>=2.12.0; extra == "dev"
Requires-Dist: flake8>=3.9.0; extra == "dev"
Requires-Dist: black>=21.5b2; extra == "dev"
Dynamic: author
Dynamic: author-email
Dynamic: classifier
Dynamic: description
Dynamic: description-content-type
Dynamic: home-page
Dynamic: keywords
Dynamic: license
Dynamic: license-file
Dynamic: provides-extra
Dynamic: requires-dist
Dynamic: requires-python
Dynamic: summary
